async_property/__init__.py
async_property/base.py
async_property/cached.py
async_property/loader.py
async_property/proxy.py
async_property-0.2.1.dist-info/LICENSE
async_property-0.2.1.dist-info/METADATA
async_property-0.2.1.dist-info/WHEEL
async_property-0.2.1.dist-info/top_level.txt
async_property-0.2.1.dist-info/RECORD
