Metadata-Version: 2.1
Name: async-property
Version: 0.2.1
Summary: Python decorator for async properties.
Home-page: https://github.com/ryananguiano/async_property
Author: Ryan Anguiano
Author-email: ryan.anguiano@gmail.com
License: MIT license
Keywords: async_property
Platform: UNKNOWN
Classifier: Development Status :: 2 - Pre-Alpha
Classifier: Intended Audience :: Developers
Classifier: License :: OSI Approved :: MIT License
Classifier: Natural Language :: English
Classifier: Programming Language :: Python :: 3
Classifier: Programming Language :: Python :: 3.6
Classifier: Programming Language :: Python :: 3.7
